src/__init__.py
src/aliyun/__init__.py
src/aliyun/http_caller.py
src/aliyun/openapi_caller.py
src/aliyun/server.py
src/demo/__init__.py
src/demo/server.py
src/utils/__init__.py
src/utils/log_utils.py
src/utils/utils.py
mcp_python_sdk_test-0.1.2.2.dist-info/LICENSE
mcp_python_sdk_test-0.1.2.2.dist-info/METADATA
mcp_python_sdk_test-0.1.2.2.dist-info/WHEEL
mcp_python_sdk_test-0.1.2.2.dist-info/entry_points.txt
mcp_python_sdk_test-0.1.2.2.dist-info/top_level.txt
mcp_python_sdk_test-0.1.2.2.dist-info/RECORD
