Metadata-Version: 2.1
Name: mcp-python-sdk-test
Version: 0.1.2.2
Summary: mcp python sdk aliyun
Home-page: http://example.com
Author: Chen
Author-email: 872679742@qq.com
License: UNKNOWN
Platform: UNKNOWN
Classifier: Development Status :: 3 - Alpha
Classifier: Intended Audience :: Developers
Classifier: Programming Language :: Python :: 3
License-File: LICENSE
Requires-Dist: alibabacloud-tea-openapi (>=0.3.13)
Requires-Dist: anyio (>=4.8.0)
Requires-Dist: click (>=8.1.8)
Requires-Dist: httpx (>=0.28.1)
Requires-Dist: httpx-sse (>=0.4.0)
Requires-Dist: mcp (>=1.3.0)
